Workbook

Sheet README
A1: NeuroBite - Question Checklist
A2: Due-diligence questions for the founder plus discovery questions for the people who will use and buy the product.
A4: Sheets
A5: Progress | B5: Live summary (formulas) of how many questions are answered per section.
A6: Internal Checklist | B6: 62 questions for the founder to ask doctors, suppliers, lawyers, customers, and so on.
A7: Employee Interviews | B7: 61 questions for the end users (office employees): daily routine, sleep, allergies, supplement history, voluntary health screening, concept reaction, privacy and culture. No price questions.
A8: Buyer Interviews | B8: 25 questions for HR, procurement, facilities and legal at customer companies (decision process, compliance, privacy, operations, evidence). No price questions.
A9: Pilot Follow-up | B9: 14 questions to ask employees after a trial period.
A11: Legend
A12: Yellow cells | B12: Cells you edit: Status, Answer / Evidence, Owner, Due Date, Source (internal sheet) or Answer / Notes (interview sheets).
A13: Dropdowns | B13: Status: Not started / In progress / Answered / Blocked. Priority: High / Medium / Low.
A14: Do not edit | B14: Progress sheet cells are formulas and update automatically.
A16: Example of a filled-in row (Internal Checklist)
A17: Question | B17: Priority | C17: Status | D17: Answer / Evidence | E17: Owner | F17: Due date | G17: Source
A18: Do we hold evidence for the 'FDA' statement? | B18: High | C18: Answered | D18: No. FDA does not certify supplements. Statement removed from site on 2026-10-15. | E18: Yusuf | F18: 2026-10-15 | G18: Site commit / lawyer email
A20: Interview tips
A21: - | B21: Ask about past behavior ('what did you do last time') rather than hypotheticals ('would you buy').
A22: - | B22: Do not pitch or quote health benefits during interviews; you are collecting facts, not selling.
A23: - | B23: Never collect medical details. If someone mentions a condition or medication, tell them to ask their doctor.
A24: - | B24: Make it clear that participation is voluntary and answers are anonymous in any report.
A25: - | B25: Interview 8-12 employees and 5-8 buyers before spending money on stock.
A27: Notes and assumptions
A28: - | B28: UAE regulator names and requirements in this file (MOHAP, Dubai Municipality, ADAFSA, PDPL) are items to VERIFY with a local regulatory consultant or lawyer; they are not confirmed rules.
A29: - | B29: This checklist is a planning tool, not medical or legal advice. Dose, interaction and safety questions must be answered by a qualified physician or clinical pharmacist.
A30: - | B30: The health-screening part of the Employee Interviews sheet collects sensitive personal data. Keep it voluntary, always allow 'prefer not to say', store answers separately from HR systems, and let only the medical advisor review them. Check UAE data-protection (PDPL) requirements with a lawyer first.
A31: - | B31: Allergy and health 'red flag' notes are screening suggestions for the medical advisor, not clinical decisions.
A32: - | B32: Based on a review of the NeuroBite website content and the founder's product plan (October 2026).

Sheet Progress
A1: Section | B1: Total | C1: Answered | D1: In progress | E1: Blocked | F1: Not started | G1: % answered | H1: High priority still open
A2: A. Formula & Safety | B2: =COUNTIFS('Internal Checklist'!$B$2:$B$63,$A2) -> 10 | C2: =COUNTIFS('Internal Checklist'!$B$2:$B$63,$A2,'Internal Checklist'!$F$2:$F$63,"Answered") -> 0 | D2: =COUNTIFS('Internal Checklist'!$B$2:$B$63,$A2,'Internal Checklist'!$F$2:$F$63,"In progress") -> 0 | E2: =COUNTIFS('Internal Checklist'!$B$2:$B$63,$A2,'Internal Checklist'!$F$2:$F$63,"Blocked") -> 0 | F2: =COUNTIFS('Internal Checklist'!$B$2:$B$63,$A2,'Internal Checklist'!$F$2:$F$63,"Not started") -> 10 | G2: =IFERROR(C2/B2,0) -> 0 | H2: =COUNTIFS('Internal Checklist'!$B$2:$B$63,$A2,'Internal Checklist'!$E$2:$E$63,"High")-COUNTIFS('Internal Checklist'!$B$2:$B$63,$A2,'Internal Checklist'!$E$2:$E$63,"High",'Internal Checklist'!$F$2:$F$63,"Answered") -> 7
A3: B. Sourcing & Quality | B3: =COUNTIFS('Internal Checklist'!$B$2:$B$63,$A3) -> 7 | C3: =COUNTIFS('Internal Checklist'!$B$2:$B$63,$A3,'Internal Checklist'!$F$2:$F$63,"Answered") -> 0 | D3: =COUNTIFS('Internal Checklist'!$B$2:$B$63,$A3,'Internal Checklist'!$F$2:$F$63,"In progress") -> 0 | E3: =COUNTIFS('Internal Checklist'!$B$2:$B$63,$A3,'Internal Checklist'!$F$2:$F$63,"Blocked") -> 0 | F3: =COUNTIFS('Internal Checklist'!$B$2:$B$63,$A3,'Internal Checklist'!$F$2:$F$63,"Not started") -> 7 | G3: =IFERROR(C3/B3,0) -> 0 | H3: =COUNTIFS('Internal Checklist'!$B$2:$B$63,$A3,'Internal Checklist'!$E$2:$E$63,"High")-COUNTIFS('Internal Checklist'!$B$2:$B$63,$A3,'Internal Checklist'!$E$2:$E$63,"High",'Internal Checklist'!$F$2:$F$63,"Answered") -> 4
A4: C. Inventory, Shelf Life & Storage | B4: =COUNTIFS('Internal Checklist'!$B$2:$B$63,$A4) -> 7 | C4: =COUNTIFS('Internal Checklist'!$B$2:$B$63,$A4,'Internal Checklist'!$F$2:$F$63,"Answered") -> 0 | D4: =COUNTIFS('Internal Checklist'!$B$2:$B$63,$A4,'Internal Checklist'!$F$2:$F$63,"In progress") -> 0 | E4: =COUNTIFS('Internal Checklist'!$B$2:$B$63,$A4,'Internal Checklist'!$F$2:$F$63,"Blocked") -> 0 | F4: =COUNTIFS('Internal Checklist'!$B$2:$B$63,$A4,'Internal Checklist'!$F$2:$F$63,"Not started") -> 7 | G4: =IFERROR(C4/B4,0) -> 0 | H4: =COUNTIFS('Internal Checklist'!$B$2:$B$63,$A4,'Internal Checklist'!$E$2:$E$63,"High")-COUNTIFS('Internal Checklist'!$B$2:$B$63,$A4,'Internal Checklist'!$E$2:$E$63,"High",'Internal Checklist'!$F$2:$F$63,"Answered") -> 7
A5: D. Legal & Licensing | B5: =COUNTIFS('Internal Checklist'!$B$2:$B$63,$A5) -> 6 | C5: =COUNTIFS('Internal Checklist'!$B$2:$B$63,$A5,'Internal Checklist'!$F$2:$F$63,"Answered") -> 0 | D5: =COUNTIFS('Internal Checklist'!$B$2:$B$63,$A5,'Internal Checklist'!$F$2:$F$63,"In progress") -> 0 | E5: =COUNTIFS('Internal Checklist'!$B$2:$B$63,$A5,'Internal Checklist'!$F$2:$F$63,"Blocked") -> 0 | F5: =COUNTIFS('Internal Checklist'!$B$2:$B$63,$A5,'Internal Checklist'!$F$2:$F$63,"Not started") -> 6 | G5: =IFERROR(C5/B5,0) -> 0 | H5: =COUNTIFS('Internal Checklist'!$B$2:$B$63,$A5,'Internal Checklist'!$E$2:$E$63,"High")-COUNTIFS('Internal Checklist'!$B$2:$B$63,$A5,'Internal Checklist'!$E$2:$E$63,"High",'Internal Checklist'!$F$2:$F$63,"Answered") -> 5
A6: E. Claims & Labeling | B6: =COUNTIFS('Internal Checklist'!$B$2:$B$63,$A6) -> 5 | C6: =COUNTIFS('Internal Checklist'!$B$2:$B$63,$A6,'Internal Checklist'!$F$2:$F$63,"Answered") -> 0 | D6: =COUNTIFS('Internal Checklist'!$B$2:$B$63,$A6,'Internal Checklist'!$F$2:$F$63,"In progress") -> 0 | E6: =COUNTIFS('Internal Checklist'!$B$2:$B$63,$A6,'Internal Checklist'!$F$2:$F$63,"Blocked") -> 0 | F6: =COUNTIFS('Internal Checklist'!$B$2:$B$63,$A6,'Internal Checklist'!$F$2:$F$63,"Not started") -> 5 | G6: =IFERROR(C6/B6,0) -> 0 | H6: =COUNTIFS('Internal Checklist'!$B$2:$B$63,$A6,'Internal Checklist'!$E$2:$E$63,"High")-COUNTIFS('Internal Checklist'!$B$2:$B$63,$A6,'Internal Checklist'!$E$2:$E$63,"High",'Internal Checklist'!$F$2:$F$63,"Answered") -> 4
A7: F. Halal, Allergens & Dietary | B7: =COUNTIFS('Internal Checklist'!$B$2:$B$63,$A7) -> 5 | C7: =COUNTIFS('Internal Checklist'!$B$2:$B$63,$A7,'Internal Checklist'!$F$2:$F$63,"Answered") -> 0 | D7: =COUNTIFS('Internal Checklist'!$B$2:$B$63,$A7,'Internal Checklist'!$F$2:$F$63,"In progress") -> 0 | E7: =COUNTIFS('Internal Checklist'!$B$2:$B$63,$A7,'Internal Checklist'!$F$2:$F$63,"Blocked") -> 0 | F7: =COUNTIFS('Internal Checklist'!$B$2:$B$63,$A7,'Internal Checklist'!$F$2:$F$63,"Not started") -> 5 | G7: =IFERROR(C7/B7,0) -> 0 | H7: =COUNTIFS('Internal Checklist'!$B$2:$B$63,$A7,'Internal Checklist'!$E$2:$E$63,"High")-COUNTIFS('Internal Checklist'!$B$2:$B$63,$A7,'Internal Checklist'!$E$2:$E$63,"High",'Internal Checklist'!$F$2:$F$63,"Answered") -> 3
A8: G. Customer Company (HR / Legal) | B8: =COUNTIFS('Internal Checklist'!$B$2:$B$63,$A8) -> 5 | C8: =COUNTIFS('Internal Checklist'!$B$2:$B$63,$A8,'Internal Checklist'!$F$2:$F$63,"Answered") -> 0 | D8: =COUNTIFS('Internal Checklist'!$B$2:$B$63,$A8,'Internal Checklist'!$F$2:$F$63,"In progress") -> 0 | E8: =COUNTIFS('Internal Checklist'!$B$2:$B$63,$A8,'Internal Checklist'!$F$2:$F$63,"Blocked") -> 0 | F8: =COUNTIFS('Internal Checklist'!$B$2:$B$63,$A8,'Internal Checklist'!$F$2:$F$63,"Not started") -> 5 | G8: =IFERROR(C8/B8,0) -> 0 | H8: =COUNTIFS('Internal Checklist'!$B$2:$B$63,$A8,'Internal Checklist'!$E$2:$E$63,"High")-COUNTIFS('Internal Checklist'!$B$2:$B$63,$A8,'Internal Checklist'!$E$2:$E$63,"High",'Internal Checklist'!$F$2:$F$63,"Answered") -> 5
A9: H. Operations & Logistics | B9: =COUNTIFS('Internal Checklist'!$B$2:$B$63,$A9) -> 5 | C9: =COUNTIFS('Internal Checklist'!$B$2:$B$63,$A9,'Internal Checklist'!$F$2:$F$63,"Answered") -> 0 | D9: =COUNTIFS('Internal Checklist'!$B$2:$B$63,$A9,'Internal Checklist'!$F$2:$F$63,"In progress") -> 0 | E9: =COUNTIFS('Internal Checklist'!$B$2:$B$63,$A9,'Internal Checklist'!$F$2:$F$63,"Blocked") -> 0 | F9: =COUNTIFS('Internal Checklist'!$B$2:$B$63,$A9,'Internal Checklist'!$F$2:$F$63,"Not started") -> 5 | G9: =IFERROR(C9/B9,0) -> 0 | H9: =COUNTIFS('Internal Checklist'!$B$2:$B$63,$A9,'Internal Checklist'!$E$2:$E$63,"High")-COUNTIFS('Internal Checklist'!$B$2:$B$63,$A9,'Internal Checklist'!$E$2:$E$63,"High",'Internal Checklist'!$F$2:$F$63,"Answered") -> 0
A10: I. Finance | B10: =COUNTIFS('Internal Checklist'!$B$2:$B$63,$A10) -> 5 | C10: =COUNTIFS('Internal Checklist'!$B$2:$B$63,$A10,'Internal Checklist'!$F$2:$F$63,"Answered") -> 0 | D10: =COUNTIFS('Internal Checklist'!$B$2:$B$63,$A10,'Internal Checklist'!$F$2:$F$63,"In progress") -> 0 | E10: =COUNTIFS('Internal Checklist'!$B$2:$B$63,$A10,'Internal Checklist'!$F$2:$F$63,"Blocked") -> 0 | F10: =COUNTIFS('Internal Checklist'!$B$2:$B$63,$A10,'Internal Checklist'!$F$2:$F$63,"Not started") -> 5 | G10: =IFERROR(C10/B10,0) -> 0 | H10: =COUNTIFS('Internal Checklist'!$B$2:$B$63,$A10,'Internal Checklist'!$E$2:$E$63,"High")-COUNTIFS('Internal Checklist'!$B$2:$B$63,$A10,'Internal Checklist'!$E$2:$E$63,"High",'Internal Checklist'!$F$2:$F$63,"Answered") -> 4
A11: J. Evidence & Market | B11: =COUNTIFS('Internal Checklist'!$B$2:$B$63,$A11) -> 4 | C11: =COUNTIFS('Internal Checklist'!$B$2:$B$63,$A11,'Internal Checklist'!$F$2:$F$63,"Answered") -> 0 | D11: =COUNTIFS('Internal Checklist'!$B$2:$B$63,$A11,'Internal Checklist'!$F$2:$F$63,"In progress") -> 0 | E11: =COUNTIFS('Internal Checklist'!$B$2:$B$63,$A11,'Internal Checklist'!$F$2:$F$63,"Blocked") -> 0 | F11: =COUNTIFS('Internal Checklist'!$B$2:$B$63,$A11,'Internal Checklist'!$F$2:$F$63,"Not started") -> 4 | G11: =IFERROR(C11/B11,0) -> 0 | H11: =COUNTIFS('Internal Checklist'!$B$2:$B$63,$A11,'Internal Checklist'!$E$2:$E$63,"High")-COUNTIFS('Internal Checklist'!$B$2:$B$63,$A11,'Internal Checklist'!$E$2:$E$63,"High",'Internal Checklist'!$F$2:$F$63,"Answered") -> 3
A12: K. Insurance & Crisis | B12: =COUNTIFS('Internal Checklist'!$B$2:$B$63,$A12) -> 3 | C12: =COUNTIFS('Internal Checklist'!$B$2:$B$63,$A12,'Internal Checklist'!$F$2:$F$63,"Answered") -> 0 | D12: =COUNTIFS('Internal Checklist'!$B$2:$B$63,$A12,'Internal Checklist'!$F$2:$F$63,"In progress") -> 0 | E12: =COUNTIFS('Internal Checklist'!$B$2:$B$63,$A12,'Internal Checklist'!$F$2:$F$63,"Blocked") -> 0 | F12: =COUNTIFS('Internal Checklist'!$B$2:$B$63,$A12,'Internal Checklist'!$F$2:$F$63,"Not started") -> 3 | G12: =IFERROR(C12/B12,0) -> 0 | H12: =COUNTIFS('Internal Checklist'!$B$2:$B$63,$A12,'Internal Checklist'!$E$2:$E$63,"High")-COUNTIFS('Internal Checklist'!$B$2:$B$63,$A12,'Internal Checklist'!$E$2:$E$63,"High",'Internal Checklist'!$F$2:$F$63,"Answered") -> 2
A13: TOTAL | B13: =SUM(B2:B12) -> 62 | C13: =SUM(C2:C12) -> 0 | D13: =SUM(D2:D12) -> 0 | E13: =SUM(E2:E12) -> 0 | F13: =SUM(F2:F12) -> 62 | G13: =IFERROR(C13/B13,0) -> 0 | H13: =SUM(H2:H12) -> 44
A15: All figures on this sheet are formulas driven by the Status and Priority columns of the Internal Checklist sheet.

Sheet Internal Checklist
A1: # | B1: Section | C1: Question | D1: Ask whom | E1: Priority | F1: Status | G1: Answer / Evidence | H1: Owner | I1: Due date | J1: Source / Document
A2: 1 | B2: A. Formula & Safety | C2: What are the effective AND safe daily dose ranges for Lion's Mane, Rhodiola, Omega-3 (DHA), CoQ10 and B12 in healthy adults? | D2: Physician / Clinical pharmacist / Dietitian | E2: High | F2: Not started
A3: 2 | B3: A. Formula & Safety | C3: Is there evidence for taking this exact combination together, every day, long term? | D3: Physician / Clinical pharmacist / Dietitian | E3: High | F3: Not started
A4: 3 | B4: A. Formula & Safety | C4: Which medications interact with each ingredient (antidepressants, anticoagulants, blood-pressure, thyroid, diabetes, hormonal)? | D4: Physician / Clinical pharmacist / Dietitian | E4: High | F4: Not started
A5: 4 | B5: A. Formula & Safety | C5: Who must NOT receive the tray (pregnancy, breastfeeding, epilepsy, bipolar disorder, immunosuppression, pre-surgery, fish or mushroom allergy)? | D5: Physician / Clinical pharmacist / Dietitian | E5: High | F5: Not started
A6: 5 | B6: A. Formula & Safety | C6: Does the dose need adjusting for age or body weight? | D6: Physician / Clinical pharmacist / Dietitian | E6: Medium | F6: Not started
A7: 6 | B7: A. Formula & Safety | C7: How do we manage double-dosing with supplements employees already take? | D7: Physician / Clinical pharmacist / Dietitian | E7: High | F7: Not started
A8: 7 | B8: A. Formula & Safety | C8: Do caffeine/theobromine (dark chocolate) combined with Rhodiola cause sleep or heart-rate issues? | D8: Physician / Clinical pharmacist / Dietitian | E8: Medium | F8: Not started
A9: 8 | B9: A. Formula & Safety | C9: What is the best time of day for each item, and what happens if it is taken late in the day? | D9: Physician / Clinical pharmacist / Dietitian | E9: Medium | F9: Not started
A10: 9 | B10: A. Formula & Safety | C10: How will adverse events be reported, recorded and reviewed, and by whom? | D10: Physician / Clinical pharmacist / Dietitian | E10: High | F10: Not started
A11: 10 | B11: A. Formula & Safety | C11: Which components are mandatory vs. optional, and who signs off on that decision? | D11: Physician / Clinical pharmacist / Dietitian | E11: High | F11: Not started
A12: 11 | B12: B. Sourcing & Quality | C12: Are the products officially distributed in the UAE? Is Thorne (and each other brand) available through authorized channels? | D12: Distributor / Manufacturer | E12: High | F12: Not started
A13: 12 | B13: B. Sourcing & Quality | C13: Do the brands allow bulk purchase, repackaging and commercial use, in writing? | D13: Distributor / Manufacturer | E13: High | F13: Not started
... A63: 62 | B63: K. Insurance & Crisis | C63: Who is the on-call medical advisor for adverse reactions? | D63: Insurance broker / PR advisor | E63: High | F63: Not started

Sheet Employee Interviews
A1: # | B1: Topic | C1: Question | D1: Answer type | E1: Why we ask | F1: Red flag / watch for | G1: Answer / Notes
A2: E1 | B2: Consent & ground rules | C2: Participation is voluntary, you can skip any question ('prefer not to say'), and answers are confidential. Do you agree to continue? | D2: Yes/No | E2: Informed consent and trust. | F2: Any 'No': stop and thank them.
A3: E2 | B3: Consent & ground rules | C3: May we contact you again for a pilot or follow-up? Which channel do you prefer? | D3: Yes/No + choice | E3: Pilot recruitment. | F3: -
A4: E3 | B4: Profile & work schedule | C4: What is your age range? | D4: Choice (18-24 / 25-34 / 35-44 / 45-54 / 55+) | E4: Tolerance, habits and product tuning. | F4: -
A5: E4 | B5: Profile & work schedule | C5: What best describes your work: desk-based, mixed, field/shift, other? | D5: Choice | E5: Usage pattern and delivery fit. | F5: Mostly field/shift: tray may not reach them.
A6: E5 | B6: Profile & work schedule | C6: Which days are you usually in the office, and what time do you arrive? | D6: Open | E6: Matches 8:30 AM delivery and avoids waste. | F6: Arrives after 10:00 or mostly remote.
A7: E6 | B7: Profile & work schedule | C7: How many hours a day do you sit at a desk or screen? | D7: Number | E7: Context for energy and focus needs. | F7: -
A8: E7 | B8: Profile & work schedule | C8: How would you rate your work stress right now (1 = low, 5 = very high)? | D8: Scale 1-5 | E8: Baseline for the focus/stress promise. | F8: Very low stress: weak need.
A9: E8 | B9: Daily routine & eating | C9: Walk me through a typical workday: what do you eat and drink, and when? | D9: Open | E9: Baseline eating and drinking habits. | F9: Strict routines or no snacking (low adoption).
A10: E9 | B10: Daily routine & eating | C10: How often per week do you eat breakfast, lunch at the office, and an afternoon snack? | D10: Number per meal | E10: Where the tray fits in the day. | F10: Skips snacks entirely.
A11: E10 | B11: Daily routine & eating | C11: How often do you eat out, order delivery, or bring food from home? | D11: Choice | E11: Competing food sources. | F11: Always brings own food.
A12: E11 | B12: Daily routine & eating | C12: Do you follow any fasting pattern (intermittent fasting, religious fasts, Ramadan, Monday/Thursday fasts)? | D12: Multi-choice | E12: Tray cannot be used while fasting. | F12: Fasting several days a week.
A13: E12 | B13: Daily routine & eating | C13: Do you follow any particular diet: halal-only, vegetarian, vegan, pescatarian, gluten-free, lactose-free, low-carb, keto, other? | D13: Multi-choice | E13: Defines mandatory product options. | F13: Vegan or keto: core tray unsuitable.
... A62: E61 | B62: Wrap-up | C62: What question should we have asked you that we have not? | D62: Open | E62: Surfaces blind spots. | F62: -

Sheet Buyer Interviews
A1: # | B1: Topic | C1: Question | D1: Answer type | E1: Why we ask | F1: Red flag / watch for | G1: Answer / Notes
A2: B1 | B2: Decision process | C2: Who must approve a new vendor (HR, finance, legal, health & safety), and how long does it take? | D2: Open | E2: Maps the sales cycle. | F2: 4+ approvers or 6+ months.
A3: B2 | B3: Decision process | C3: What would this replace: snacks, fruit, gym stipend, or nothing? | D3: Open | E3: Defines the competing spend. | F3: Nothing replaced: needs new budget.
A4: B3 | B4: Decision process | C4: What contract length and cancellation terms are acceptable? | D4: Open | E4: Inventory and churn planning. | F4: Cancel-anytime with no notice.
A5: B4 | B5: Decision process | C5: What would a successful pilot look like, in numbers? | D5: Open | E5: Defines the success metric up front. | F5: No measurable target.
A6: B5 | B6: Decision process | C6: Who is the internal champion, and who is the likely blocker? | D6: Open | E6: Stakeholder map. | F6: Legal or health & safety unaware.
A7: B6 | B7: Compliance & procurement | C7: Which documents do you require from food/supplement vendors (trade license, HACCP/ISO, municipality permit, halal certificates, insurance, CoAs)? | D7: Open | E7: Shows readiness gaps. | F7: We cannot produce the documents.
A8: B7 | B8: Compliance & procurement | C8: Do you have a policy on employer-provided supplements or medical-type products? Who must review it? | D8: Open | E8: Policy blockers. | F8: Policy forbids it.
A9: B8 | B9: Compliance & procurement | C9: What liability or insurance minimum do you require from vendors? | D9: Open | E9: Insurance requirement. | F9: Above our current cover.
A10: B9 | B10: Compliance & procurement | C10: Do you require medical or allergy screening before employees receive supplements? | D10: Yes/No + open | E10: Onboarding workload. | F10: Mandatory screening makes the model heavy.
A11: B10 | B11: Compliance & procurement | C11: How do you handle allergen/food-safety incidents, and what would you expect from us? | D11: Open | E11: Incident expectations. | F11: Unlimited liability expected.
A12: B11 | B12: Privacy & data | C12: What employee data are you willing to collect or receive (none / aggregate only / individual)? | D12: Choice | E12: Data model fit. | F12: Wants individual health data.
A13: B12 | B13: Privacy & data | C13: Who would own and see QR/wellness data, and which data-protection rules (UAE PDPL) apply? | D13: Open | E13: Legal exposure. | F13: No clear data owner.
... A26: B25 | B26: Close | C26: What did we not ask that we should have? | D26: Open | E26: Blind spots. | F26: -

Sheet Pilot Follow-up
A1: # | B1: Topic | C1: Question | D1: Answer type | E1: Why we ask | F1: Red flag / watch for | G1: Answer / Notes
A2: P1 | B2: Usage | C2: On how many of the pilot days did you use the tray? | D2: Number | E2: Real adoption rate. | F2: Below 50%.
A3: P2 | B3: Usage | C3: Which items did you use, and which did you skip? Why? | D3: Open | E3: Shows which items to cut. | F3: Capsules skipped most.
A4: P3 | B4: Safety | C4: Did you notice any side effects (stomach upset, sleep change, headache, racing heart, skin irritation)? Please describe. | D4: Open | E4: Safety signal. | F4: ANY serious effect: stop and escalate to the medical advisor.
A5: P4 | B5: Safety | C5: Did the labels and ingredient/allergen information feel clear? | D5: Scale 1-5 | E5: Label quality. | F5: Score 3 or lower.
A6: P5 | B6: Effect | C6: Compared with before the pilot, how is your afternoon focus (1 = worse, 5 = better)? | D6: Scale 1-5 | E6: Perceived effect (self-reported only). | F6: No change or worse.
A7: P6 | B7: Effect | C7: Compared with before the pilot, how is your energy level (1 = worse, 5 = better)? | D7: Scale 1-5 | E7: Perceived effect. | F7: No change or worse.
A8: P7 | B8: Effect | C8: Has your sleep changed (1 = worse, 5 = better)? | D8: Scale 1-5 | E8: Caffeine/Rhodiola effect. | F8: Score 2 or lower.
A9: P8 | B9: Product | C9: Rate taste and portion for each item (1-5). | D9: Scale 1-5 per item | E9: Product tuning. | F9: Chocolate or water rated low.
A10: P9 | B10: Product | C10: Was the 8:30 AM delivery on time and complete? | D10: Yes/No + open | E10: Service quality. | F10: Late or missing items.
A11: P10 | B11: Product | C11: Did you use the QR routine? What made it easy or hard? | D11: Open | E11: Digital ritual adoption. | F11: Used under 20% of days.
A12: P11 | B12: Experience | C12: Did you feel any pressure to participate? | D12: Yes/No + open | E12: Coercion risk. | F12: Any 'Yes'.
A13: P12 | B13: Overall | C13: Would you want to continue after the pilot? Why or why not? | D13: Yes/No/Maybe + open | E13: Retention signal. | F13: Mostly No or Maybe.
... A15: P14 | B15: Overall | C15: What one thing should we remove or change? | D15: Open | E15: Prioritises product changes. | F15: -
